modea/Algorithms.py
modea/Individual.py
modea/Mutation.py
modea/Parameters.py
modea/Recombination.py
modea/Sampling.py
modea/Selection.py
modea/Utils.py
modea/__init__.py
ModEA-0.5.0.dist-info/LICENSE
ModEA-0.5.0.dist-info/METADATA
ModEA-0.5.0.dist-info/WHEEL
ModEA-0.5.0.dist-info/top_level.txt
ModEA-0.5.0.dist-info/RECORD
