Metadata-Version: 2.1
Name: ModEA
Version: 0.5.0
Summary: A modular evolutionary algorithm framework, mostly tailored to a modular implementation of the CMA-ES
Home-page: https://github.com/sjvrijn/ModEA
Author: Sander van Rijn
Author-email: svr003@gmail.com
License: UNKNOWN
Platform: UNKNOWN
Classifier: Programming Language :: Python :: 2
Classifier: Programming Language :: Python :: 3.6
Classifier: Programming Language :: Python :: 3.7
Classifier: License :: OSI Approved :: MIT License
Classifier: Operating System :: OS Independent
License-File: LICENSE
